asset_downloader/__init__.py
asset_downloader/__main__.py
asset_downloader/giphy.py
asset_downloader/iconfinder.py
asset_downloader/pexels.py
asset_downloader/pixabay.py
asset_downloader/unsplash.py
asset_downloader/youtube.py
asset_downloader-0.1.4.dist-info/entry_points.txt
asset_downloader-0.1.4.dist-info/WHEEL
asset_downloader-0.1.4.dist-info/METADATA
asset_downloader-0.1.4.dist-info/RECORD
