Metadata-Version: 2.1
Name: asset-downloader
Version: 0.1.4
Summary: My editing pal
License: MIT
Author: Antonio Feregrino
Author-email: antonio.feregrino@gmail.com
Requires-Python: >=3.8,<4.0
Classifier: License :: OSI Approved :: MIT License
Classifier: Programming Language :: Python :: 3
Classifier: Programming Language :: Python :: 3.10
Classifier: Programming Language :: Python :: 3.8
Classifier: Programming Language :: Python :: 3.9
Requires-Dist: python-slugify
Requires-Dist: pytube
Requires-Dist: requests
Requires-Dist: typer
